hotmetal/__init__.py
hotmetal/utils/__init__.py
hotmetal/utils/classnames.py
hotmetal/utils/find.py
hotmetal-1.0.0.dist-info/LICENSE
hotmetal-1.0.0.dist-info/METADATA
hotmetal-1.0.0.dist-info/WHEEL
hotmetal-1.0.0.dist-info/top_level.txt
hotmetal-1.0.0.dist-info/RECORD
