Metadata-Version: 2.1
Name: hotmetal
Version: 1.0.0
Summary: UNKNOWN
Home-page: https://github.com/j4mie/hotmetal
Author: Jamie Matthews
Author-email: jamie@mtth.org
License: BSD
Project-URL: Changelog, https://github.com/j4mie/hotmetal/releases
Project-URL: Issues, https://github.com/j4mie/hotmetal/issues
Platform: UNKNOWN
Requires-Python: >=3.6
